pyvpd/__init__.py
pyvpd/rectification.py
pyvpd/vp_detector.py
pyvpd-0.1.2.dist-info/LICENSE
pyvpd-0.1.2.dist-info/METADATA
pyvpd-0.1.2.dist-info/WHEEL
pyvpd-0.1.2.dist-info/top_level.txt
pyvpd-0.1.2.dist-info/RECORD
