Metadata-Version: 2.1
Name: pyvpd
Version: 0.1.2
Summary: Vanishing Point Detector
Home-page: https://github.com/SajjadAemmi/pyvpd
Author: Sajjad Aemmi
Author-email: sajjadaemmi@gmail.com
License-File: LICENSE
Requires-Dist: scikit-image
Requires-Dist: numpy
Requires-Dist: matplotlib
